rhopca/__init__.py
rhopca/core.py
rhopca-0.1.0.dist-info/licenses/LICENSE
rhopca-0.1.0.dist-info/METADATA
rhopca-0.1.0.dist-info/WHEEL
rhopca-0.1.0.dist-info/top_level.txt
rhopca-0.1.0.dist-info/RECORD
