Metadata-Version: 2.4
Name: rhopca
Version: 0.1.0
Summary: Target vs background variance dimensionality reduction for single-cell analyses.
Author-email: "Maria T. Carilli" <mcarilli@caltech.edu>
License: BSD 2-Clause License
Project-URL: Homepage, https://github.com/pachterlab/rhopca
Project-URL: Issues, https://github.com/pachterlab/rhopca/issues
Requires-Python: >=3.9
License-File: LICENSE
Requires-Dist: numpy>=1.23
Requires-Dist: scipy>=1.9
Requires-Dist: matplotlib>=3.7
Requires-Dist: seaborn>=0.12
Requires-Dist: anndata>=0.9
Requires-Dist: scanpy>=1.9
Dynamic: license-file
